stamphq/__init__.py
stamphq/client.py
stamphq/exceptions.py
stamphq/models.py
stamphq-0.0.1.dist-info/LICENSE
stamphq-0.0.1.dist-info/METADATA
stamphq-0.0.1.dist-info/WHEEL
stamphq-0.0.1.dist-info/top_level.txt
stamphq-0.0.1.dist-info/RECORD
