Metadata-Version: 2.1
Name: stamphq
Version: 0.0.1
Summary: python SDK for stampHQ email send APIs.
Author-email: Gowtham Gopalakrishnan <sdk@stamphq.app>
Project-URL: Homepage, https://github.com/stamphq/python-sdk
Project-URL: Bug Tracker, https://github.com/stamphq/python-sdk/issues
Keywords: stamphq,send email,email,email REST API
Classifier: Programming Language :: Python :: 3
Classifier: Operating System :: OS Independent
Classifier: Intended Audience :: Developers
Classifier: Development Status :: 2 - Pre-Alpha
Classifier: Topic :: Communications :: Email
Requires-Python: >=3.7
License-File: LICENSE
Requires-Dist: requests
Requires-Dist: pytest
Requires-Dist: setuptools
